{"weather":{"suggestions":[{"title":"Weather for Minneapolis","url":"https://www.accuweather.com/en/us/minneapolis-mn/55415/current-weather/348794?lang=en-us&partner=web_mozilla_adc","provider":"accuweather","is_sponsored":false,"score":0.3,"city_name":"Minneapolis","region_code":"MN","current_conditions":{"url":"https://www.accuweather.com/en/us/minneapolis-mn/55415/current-weather/348794?lang=en-us&partner=web_mozilla_adc","summary":"Sunny","icon_id":1,"temperature":{"c":-14,"f":6}},"forecast":{"url":"https://www.accuweather.com/en/us/minneapolis-mn/55415/daily-weather-forecast/348794?lang=en-us&partner=web_mozilla_adc","summary":"The cold wave will continue through tomorrow","high":{"c":-8,"f":18},"low":{"c":-19,"f":-2}},"request_id":"1cd5823b6b7a490985329e11f425639c","source":"merino"}],"lastUpdated":1773669297312},"locationData":{"city":"Minneapolis","adminArea":"","country":""}}